[
  {
    "cppcheck_version": "2.10",
    "verbose": "Non-pure function: \u0027se_readc\u0027 is called inside assert statement. Assert statements are removed from release builds so the code inside assert statement is not executed. If the code is needed also in release builds, this is a bug.",
    "cwe": "398",
    "file_path": "tmp_github/jdh-8/misc/aep/old/main.c",
    "line_number": "165",
    "column_number": "13",
    "tool_name": "cppcheck",
    "git_link": "https://github.com/jdah/jdh-8.git",
    "commit_id": "f253853e740bd4bfa83041fbf73568a0d32b1141",
    "commit_id_repair": "b5f7827e6181a5b37533012aad7acfc7881f4707",
    "warning_message": "Assert statement calls a function which may have desired side effects: \u0027se_readc\u0027.",
    "hash_id": "d644c120470b79122d3fffa0f1cc334fb92a852f34e3b11014139db8ba6d364a",
    "bug_severity": "warning",
    "bug_type": "assertWithSideEffect"
  },
  {
    "cppcheck_version": "2.10",
    "verbose": "Boolean value assigned to pointer.",
    "cwe": "587",
    "file_path": "tmp_github/jdh-8/misc/avt/main.c",
    "line_number": "172",
    "column_number": "23",
    "tool_name": "cppcheck",
    "git_link": "https://github.com/jdah/jdh-8.git",
    "commit_id": "f253853e740bd4bfa83041fbf73568a0d32b1141",
    "commit_id_repair": "b5f7827e6181a5b37533012aad7acfc7881f4707",
    "warning_message": "Boolean value assigned to pointer.",
    "hash_id": "13a368d17fcd8c5c7720f37f3501bde6118c87a973ea4d26373c20a6bdea2a0f",
    "bug_severity": "error",
    "bug_type": "assignBoolToPointer"
  },
  {
    "cppcheck_version": "2.10",
    "verbose": "Boolean value assigned to pointer.",
    "cwe": "587",
    "file_path": "tmp_github/jdh-8/misc/avt/main.c",
    "line_number": "173",
    "column_number": "23",
    "tool_name": "cppcheck",
    "git_link": "https://github.com/jdah/jdh-8.git",
    "commit_id": "f253853e740bd4bfa83041fbf73568a0d32b1141",
    "commit_id_repair": "b5f7827e6181a5b37533012aad7acfc7881f4707",
    "warning_message": "Boolean value assigned to pointer.",
    "hash_id": "13a368d17fcd8c5c7720f37f3501bde6118c87a973ea4d26373c20a6bdea2a0f",
    "bug_severity": "error",
    "bug_type": "assignBoolToPointer"
  },
  {
    "cppcheck_version": "2.10",
    "verbose": "scanf() without field width limits can crash with huge input data. Add a field width specifier to fix this problem.\\012\\012Sample program that can crash:\\012\\012#include \u003cstdio.h\u003e\\012int main()\\012{\\012    char c[5];\\012    scanf(\"%s\", c);\\012    return 0;\\012}\\012\\012Typing in 5 or more characters may make the program crash. The correct usage here is \u0027scanf(\"%4s\", c);\u0027, as the maximum field width does not include the terminating null byte.\\012Source: http://linux.die.net/man/3/scanf\\012Source: http://www.opensource.apple.com/source/xnu/xnu-1456.1.26/libkern/stdio/scanf.c",
    "cwe": "119",
    "file_path": "tmp_github/jdh-8/emu/win/win.c",
    "line_number": "112",
    "column_number": "2",
    "tool_name": "cppcheck",
    "git_link": "https://github.com/jdah/jdh-8.git",
    "commit_id": "05d7efcb191f66cba55a390e7af9005de95a469f",
    "commit_id_repair": "6902efb5e7042aa105dc4a323fb0cd2ee785c37b",
    "warning_message": "scanf() without field width limits can crash with huge input data.",
    "hash_id": "92179c2b0ee941323e6a8bb9bb1a2250740105dc7fb99d9a2c25eb907962223f",
    "bug_severity": "warning",
    "bug_type": "invalidscanf"
  },
  {
    "cppcheck_version": "2.10",
    "verbose": "Null pointer dereference: retval",
    "cwe": "476",
    "file_path": "tmp_github/jdh-8/emu/win/win.c",
    "line_number": "112",
    "column_number": "14",
    "info": "Null pointer dereference",
    "tool_name": "cppcheck",
    "git_link": "https://github.com/jdah/jdh-8.git",
    "commit_id": "05d7efcb191f66cba55a390e7af9005de95a469f",
    "commit_id_repair": "6902efb5e7042aa105dc4a323fb0cd2ee785c37b",
    "warning_message": "Null pointer dereference: retval",
    "hash_id": "1500c76f2d999940e432ad73d0aaa2ab5bcf00af851f82d07e01b76b829cbfb0",
    "bug_severity": "error",
    "bug_type": "nullPointer"
  },
  {
    "cppcheck_version": "2.10",
    "verbose": "Null pointer dereference: retval",
    "cwe": "476",
    "file_path": "tmp_github/jdh-8/emu/win/win.c",
    "line_number": "110",
    "column_number": "17",
    "info": "Assignment \u0027retval\u003dNULL\u0027, assigned value is 0",
    "tool_name": "cppcheck",
    "git_link": "https://github.com/jdah/jdh-8.git",
    "commit_id": "05d7efcb191f66cba55a390e7af9005de95a469f",
    "commit_id_repair": "6902efb5e7042aa105dc4a323fb0cd2ee785c37b",
    "warning_message": "Null pointer dereference: retval",
    "hash_id": "ecfd18bc8a11797babddec56744c06037cc50964a6e1b7265bb48b9cb9bfcd33",
    "bug_severity": "error",
    "bug_type": "nullPointer"
  },
  {
    "cppcheck_version": "2.10",
    "verbose": "Null pointer dereference",
    "cwe": "476",
    "file_path": "tmp_github/jdh-8/emu/win/win.c",
    "line_number": "112",
    "column_number": "14",
    "info": "Null pointer dereference",
    "tool_name": "cppcheck",
    "git_link": "https://github.com/jdah/jdh-8.git",
    "commit_id": "05d7efcb191f66cba55a390e7af9005de95a469f",
    "commit_id_repair": "6902efb5e7042aa105dc4a323fb0cd2ee785c37b",
    "warning_message": "Null pointer dereference",
    "hash_id": "bb28a4248ed25bb7217bea27ea5b723afe8ea9b4f14c4f6adc8662af7fcf3972",
    "bug_severity": "error",
    "bug_type": "nullPointer"
  }
]