[
  {
    "cppcheck_version": "2.13 dev",
    "verbose": "There is an unknown macro here somewhere. Configuration is required. If INT64_FORMAT is a macro then please configure it.",
    "file_path": "tmp_github/postgresql-hll/src/hll.c",
    "line_number": "563",
    "column_number": "40",
    "tool_name": "cppcheck",
    "git_link": "https://github.com/citusdata/postgresql-hll.git",
    "commit_id": "6d7d03cc93b292a25eaa35094c32cd9de0481922",
    "commit_id_repair": "d89a3fb48686653afe991803b4ea1c17863316d9",
    "warning_message": "There is an unknown macro here somewhere. Configuration is required. If INT64_FORMAT is a macro then please configure it.",
    "hash_id": "a45cebe5abd35909f687faa8cdafb4c3b2fc52b99149d7038a60597bd8b8398e",
    "bug_severity": "error",
    "bug_type": "unknownMacro"
  }
]